<odoo>
	<data noupdate="0">
     <!-- set constant in ir.default -->


<record id="model_fields_ocr_template_partner_name" model="model.fields.ocr.template">
    <field name="model_id" ref="model_res_partner"/>  
    <field name="model_fields_id" ref="base.field_res_partner__name"/>  
    <field name="regex">(2,1) (2,2) (2,3)</field>
</record>


<record id="model_fields_ocr_template_partner_dob" model="model.fields.ocr.template">
    <field name="model_id" ref="model_res_partner"/>  
    <field name="model_fields_id" ref="base.field_res_partner__comment"/>  
    <field name="regex">(6,1)</field>
</record>

<record id="model_fields_ocr_template_partner_fathers_name" model="model.fields.ocr.template">
    <field name="model_id" ref="model_res_partner"/>  
    <field name="model_fields_id" ref="base.field_res_partner__street"/>  
    <field name="regex">(5,1) (5,2) (5,3)</field>
</record>

<record id="model_fields_ocr_template_partner_pan_number" model="model.fields.ocr.template">
    <field name="model_id" ref="model_res_partner"/>  
    <field name="model_fields_id" ref="base.field_res_partner__ref"/>  
    <field name="regex">(8,1)</field>
</record>

<record id="model_fields_ocr_template_partner_category_id" model="model.fields.ocr.template">
    <field name="model_id" ref="model_res_partner"/>  
    <field name="model_fields_id" ref="base.field_res_partner__category_id"/>  
    <field name="regex">(8,1)</field>
</record>


<record id="ocr_template_pan" model="ocr.template">
    <field name="name">Indian Pan Card</field>
    <field name="result" type="html"><div class="container" style="overflow-x:auto;">
            <div class="row">
                <div class="col-sm-6">
                    <img style="width:100%;" src="/wk_ocr_data_fetch/static/helpers/test9_1.jpg" loading="lazy"/>
                </div>
                <div class="col-sm-6">
                    <table style="width:100%;border:1px solid black;">
            <tr>
                <th style="border:1px solid black;"></th>
                    <th style="border:1px solid black;">1</th>
                    <th style="border:1px solid black;">2</th>
                    <th style="border:1px solid black;">3</th>
                    <th style="border:1px solid black;">4</th>
                    <th style="border:1px solid black;">5</th>
                    <th style="border:1px solid black;">6</th>
            </tr>
                <tr>
                    <th style="border:1px solid black;">1</th>
                        <td style="border:1px solid black;">
                            INCOME
                        </td>
                        <td style="border:1px solid black;">
                            TAX
                        </td>
                        <td style="border:1px solid black;">
                            DEPARTMENT
                        </td>
                        <td style="border:1px solid black;">
                            GOVT.
                        </td>
                        <td style="border:1px solid black;">
                            OF
                        </td>
                        <td style="border:1px solid black;">
                            INDIA
                        </td>
                </tr>
                <tr>
                    <th style="border:1px solid black;">2</th>
                        <td style="border:1px solid black;">
                            D
                        </td>
                        <td style="border:1px solid black;">
                            MANIKANDAN
                        </td>
                        <td style="border:1px solid black;">
                        </td>
                        <td style="border:1px solid black;">
                        </td>
                        <td style="border:1px solid black;">
                        </td>
                        <td style="border:1px solid black;">
                        </td>
                </tr>
                <tr>
                    <th style="border:1px solid black;">3</th>
                        <td style="border:1px solid black;">
                        </td>
                        <td style="border:1px solid black;">
                        </td>
                        <td style="border:1px solid black;">
                        </td>
                        <td style="border:1px solid black;">
                        </td>
                        <td style="border:1px solid black;">
                        </td>
                        <td style="border:1px solid black;">
                        </td>
                </tr>
                <tr>
                    <th style="border:1px solid black;">4</th>
                        <td style="border:1px solid black;">
                        </td>
                        <td style="border:1px solid black;">
                        </td>
                        <td style="border:1px solid black;">
                        </td>
                        <td style="border:1px solid black;">
                        </td>
                        <td style="border:1px solid black;">
                        </td>
                        <td style="border:1px solid black;">
                        </td>
                </tr>
                <tr>
                    <th style="border:1px solid black;">5</th>
                        <td style="border:1px solid black;">
                            DURAISAMY
                        </td>
                        <td style="border:1px solid black;">
                        </td>
                        <td style="border:1px solid black;">
                        </td>
                        <td style="border:1px solid black;">
                        </td>
                        <td style="border:1px solid black;">
                        </td>
                        <td style="border:1px solid black;">
                        </td>
                </tr>
                <tr>
                    <th style="border:1px solid black;">6</th>
                        <td style="border:1px solid black;">
                            16/07/1986
                        </td>
                        <td style="border:1px solid black;">
                        </td>
                        <td style="border:1px solid black;">
                        </td>
                        <td style="border:1px solid black;">
                        </td>
                        <td style="border:1px solid black;">
                        </td>
                        <td style="border:1px solid black;">
                        </td>
                </tr>
                <tr>
                    <th style="border:1px solid black;">7</th>
                        <td style="border:1px solid black;">
                            Permanent
                        </td>
                        <td style="border:1px solid black;">
                            Account
                        </td>
                        <td style="border:1px solid black;">
                            Number
                        </td>
                        <td style="border:1px solid black;">
                        </td>
                        <td style="border:1px solid black;">
                        </td>
                        <td style="border:1px solid black;">
                        </td>
                </tr>
                <tr>
                    <th style="border:1px solid black;">8</th>
                        <td style="border:1px solid black;">
                            BNZPM2501F
                        </td>
                        <td style="border:1px solid black;">
                        </td>
                        <td style="border:1px solid black;">
                        </td>
                        <td style="border:1px solid black;">
                        </td>
                        <td style="border:1px solid black;">
                        </td>
                        <td style="border:1px solid black;">
                        </td>
                </tr>
                <tr>
                    <th style="border:1px solid black;">9</th>
                        <td style="border:1px solid black;">
                        </td>
                        <td style="border:1px solid black;">
                        </td>
                        <td style="border:1px solid black;">
                        </td>
                        <td style="border:1px solid black;">
                        </td>
                        <td style="border:1px solid black;">
                        </td>
                        <td style="border:1px solid black;">
                        </td>
                </tr>
        </table>
                </div>
            </div>
        </div>
    </field>
    <field name="model_fields_ids" eval="[(6, 0, [ ref('model_fields_ocr_template_partner_name'), ref('model_fields_ocr_template_partner_dob'), ref('model_fields_ocr_template_partner_fathers_name'), ref('model_fields_ocr_template_partner_pan_number')])]"/>
   

</record>

</data>
</odoo>













